deap_misl/__init__.py
deap_misl/algorithms/__init__.py
deap_misl/algorithms/moead.py
deap_misl/tools/__init__.py
deap_misl/tools/m_emo.py
deap_misl/tools/my_emo.py
deap_misl/tools/selNSGA3.py
deap_misl/tools/twodim.py
deap_misl/tools/utils.py
deap_misl-0.2.0.dist-info/LICENSE.txt
deap_misl-0.2.0.dist-info/METADATA
deap_misl-0.2.0.dist-info/WHEEL
deap_misl-0.2.0.dist-info/top_level.txt
deap_misl-0.2.0.dist-info/RECORD
