Metadata-Version: 2.1
Name: deap-misl
Version: 0.2.0
Summary: DEAP additional tooklit by MISL
Home-page: https://github.com/D-HISL/deap_misl
Author: junjis0203
Author-email: junjis0203@gmail.com
License: LGPL
Keywords: evolutionary algorithms,genetic algorithms,ga
Platform: any
Classifier: Development Status :: 4 - Beta
Classifier: Intended Audience :: Developers
Classifier: Intended Audience :: Education
Classifier: Intended Audience :: Science/Research
Classifier: License :: OSI Approved :: GNU Library or Lesser General Public License (LGPL)
Classifier: Programming Language :: Python
Classifier: Programming Language :: Python :: 3
Classifier: Topic :: Scientific/Engineering
Classifier: Topic :: Software Development
Requires-Dist: deap
